overlay_arrows_and_more/__init__.py
overlay_arrows_and_more/overlay.py
overlay_arrows_and_more-0.5.1.dist-info/licenses/LICENSE
overlay_arrows_and_more-0.5.1.dist-info/METADATA
overlay_arrows_and_more-0.5.1.dist-info/WHEEL
overlay_arrows_and_more-0.5.1.dist-info/top_level.txt
overlay_arrows_and_more-0.5.1.dist-info/RECORD
