Metadata-Version: 2.4
Name: overlay_arrows_and_more
Version: 0.5.1
Summary: overlay arrows and more
Home-page: https://github.com/beuaaa/overlay_arrows_and_more
Author: david pratmarty
Author-email: david.pratmarty@gmail.com
License: MIT
Classifier: Development Status :: 5 - Production/Stable
Classifier: Environment :: Console
Classifier: Environment :: Win32 (MS Windows)
Classifier: Intended Audience :: End Users/Desktop
Classifier: Intended Audience :: Developers
Classifier: Intended Audience :: System Administrators
Classifier: License :: OSI Approved :: MIT License
Classifier: Operating System :: Microsoft :: Windows
Classifier: Programming Language :: Python :: 2.7
Classifier: Programming Language :: Python :: 3.8
Classifier: Topic :: Software Development :: User Interfaces
Classifier: Topic :: Software Development :: Testing
License-File: LICENSE
Dynamic: author
Dynamic: author-email
Dynamic: classifier
Dynamic: description
Dynamic: description-content-type
Dynamic: home-page
Dynamic: license
Dynamic: license-file
Dynamic: summary
